<?xml version="1.0" encoding="UTF-8"?>

<item>
    <id>site:vu:il-2006</id>
    <title>Inleiding Logica 2006</title>
    <language>nl</language>
    <last-change>2006-10-17</last-change>
    <content>


<p>
Bij het vak <a href="http://www.cs.vu.nl/~tcs/il/" external="true">Inleiding Logica</a> ben
ik van september tot en met december practicum assistent.
</p>

<p>
Als je een vraag hebt over het vak, <a href="mailto:mvermaat@cs.vu.nl" external="true">mail</a>
me dan. Als je een opgave gemaakt hebt maar niet zeker weet of je antwoord
goed is kijk ik het graag even na.
</p>


<h1>Uitwerkingen</h1>


<p>
Wanneer we tijdens het werkcollege niet aan alle sommen toe komen, probeer
ik hier soms nog enkele uitwerkingen neer te zetten.
</p>


<h2>Propositielogica</h2>


<ul>
    <li>Natuurlijke deductie: <a href="files/vu/il/uitwerking-1.2-3f.pdf">1.2 3f</a>
    en <a href="files/vu/il/uitwerking-1.2-5ad.pdf">1.2 5a,d</a></li>
    <li>Semantische equivalentie: <a href="files/vu/il/uitwerking-1.5-2.pdf">1.5 2</a>,
    <a href="files/vu/il/uitwerking-1.5-5.pdf">1.5 5</a> en
    <a href="files/vu/il/uitwerking-1.5-extra2.pdf">1.5 extra opgave 2</a></li>
</ul>


<p>
(Denk bij afleidingen in plaats van de verticale strepen hele boxen zoals we gewend
zijn.)
</p>


<h2>Modale logica</h2>


<p>
Karakteriseerbaarheid van frames: <a href="files/vu/il/uitwerking-5.3-7.pdf">5.3 7</a>
en <a href="files/vu/il/uitwerking-5.3-14.pdf">5.3 14</a>
</p>


    </content>
</item>
